tho_rustypy-0.1.0.dist-info/METADATA
tho_rustypy-0.1.0.dist-info/WHEEL
tho_rustypy-0.1.0.dist-info/license_files/LICENSE
opszero_rustypy/__init__.py
opszero_rustypy/opszero_rustypy.cpython-310-darwin.so
tho_rustypy-0.1.0.dist-info/RECORD
